colorfield/__init__.py
colorfield/apps.py
colorfield/fields.py
colorfield/static/colorfield/demo.js
colorfield/templates/colorfield/index.html
django_pg_colorfield-1.0.dist-info/LICENSE
django_pg_colorfield-1.0.dist-info/METADATA
django_pg_colorfield-1.0.dist-info/WHEEL
django_pg_colorfield-1.0.dist-info/top_level.txt
django_pg_colorfield-1.0.dist-info/RECORD
