Metadata-Version: 2.1
Name: django-pg-colorfield
Version: 1.0
Summary: A ColorField to save and filter by radius Colors in RGB array in postgresql.
Home-page: https://gitlab.com/nayan32biswas/django-pg-colorfield
Author: Nayan Biswas
Author-email: nayan32biswas@gmail.com
License: MIT License
Platform: UNKNOWN
Classifier: Environment :: Web Environment
Classifier: Framework :: Django
Classifier: Framework :: Django :: 2.0
Classifier: Intended Audience :: Developers
Classifier: License :: OSI Approved :: MIT License
Classifier: Operating System :: OS Independent
Classifier: Programming Language :: Python :: 3
Classifier: Programming Language :: Python :: 3.6
Classifier: Topic :: Internet :: WWW/HTTP
Classifier: Topic :: Internet :: WWW/HTTP :: Dynamic Content
